ciphey/__init__.py
ciphey/__main__.py
ciphey/basemods/Checkers/__init__.py
ciphey/basemods/Checkers/any.py
ciphey/basemods/Checkers/brandon.py
ciphey/basemods/Checkers/entropy.py
ciphey/basemods/Checkers/ezcheck.py
ciphey/basemods/Checkers/format.py
ciphey/basemods/Checkers/gtest.py
ciphey/basemods/Checkers/human.py
ciphey/basemods/Checkers/quorum.py
ciphey/basemods/Checkers/regex.py
ciphey/basemods/Checkers/what.py
ciphey/basemods/Crackers/__init__.py
ciphey/basemods/Crackers/affine.py
ciphey/basemods/Crackers/ascii_shift.py
ciphey/basemods/Crackers/baconian.py
ciphey/basemods/Crackers/caesar.py
ciphey/basemods/Crackers/hash.py
ciphey/basemods/Crackers/rot47.py
ciphey/basemods/Crackers/soundex.py
ciphey/basemods/Crackers/vigenere.py
ciphey/basemods/Crackers/xandy.py
ciphey/basemods/Crackers/xor_single.py
ciphey/basemods/Crackers/xorcrypt.py
ciphey/basemods/Decoders/__init__.py
ciphey/basemods/Decoders/a1z26.py
ciphey/basemods/Decoders/atbash.py
ciphey/basemods/Decoders/base58_bitcoin.py
ciphey/basemods/Decoders/base58_flickr.py
ciphey/basemods/Decoders/base58_ripple.py
ciphey/basemods/Decoders/base62.py
ciphey/basemods/Decoders/base64_url.py
ciphey/basemods/Decoders/base65536.py
ciphey/basemods/Decoders/base69.py
ciphey/basemods/Decoders/base91.py
ciphey/basemods/Decoders/bases.py
ciphey/basemods/Decoders/baudot.py
ciphey/basemods/Decoders/binary.py
ciphey/basemods/Decoders/braille.py
ciphey/basemods/Decoders/brainfuck.py
ciphey/basemods/Decoders/decimal.py
ciphey/basemods/Decoders/dna.py
ciphey/basemods/Decoders/dtmf.py
ciphey/basemods/Decoders/galactic.py
ciphey/basemods/Decoders/gzip.py
ciphey/basemods/Decoders/hexadecimal.py
ciphey/basemods/Decoders/leetspeak.py
ciphey/basemods/Decoders/letters.archive
ciphey/basemods/Decoders/morse_code.py
ciphey/basemods/Decoders/multi_tap.py
ciphey/basemods/Decoders/octal.py
ciphey/basemods/Decoders/reverse.py
ciphey/basemods/Decoders/tap_code.py
ciphey/basemods/Decoders/unicode.py
ciphey/basemods/Decoders/url.py
ciphey-5.13.0.dist-info/entry_points.txt
ciphey-5.13.0.dist-info/LICENSE
ciphey-5.13.0.dist-info/WHEEL
ciphey-5.13.0.dist-info/METADATA
ciphey-5.13.0.dist-info/RECORD
