Metadata-Version: 2.1
Name: ciphey
Version: 5.13.0
Summary: Automated Decryption Tool
License: MIT
Author: Brandon
Author-email: brandon@skerritt.blog
Requires-Python: >=3.7,<4.0
Classifier: License :: OSI Approved :: MIT License
Classifier: Programming Language :: Python :: 3
Classifier: Programming Language :: Python :: 3.7
Classifier: Programming Language :: Python :: 3.8
Classifier: Programming Language :: Python :: 3.9
Requires-Dist: appdirs (>=1.4.4,<2.0.0)
Requires-Dist: base58 (>=2.0.1,<3.0.0)
Requires-Dist: base91 (>=1.0.1,<2.0.0)
Requires-Dist: cipheycore (>=0.3.2,<0.4.0)
Requires-Dist: cipheydists (>=0.3.34,<0.4.0)
Requires-Dist: click (>=7.1.2,<9.0.0)
Requires-Dist: click-spinner (>=0.1.10,<0.2.0)
Requires-Dist: flake8 (>=3.8.4,<4.0.0)
Requires-Dist: loguru (>=0.5.3,<0.6.0)
Requires-Dist: pybase62 (>=0.4.3,<0.5.0)
Requires-Dist: pylint (>=2.6.0,<3.0.0)
Requires-Dist: pywhat (>=0.2.5,<0.3.0)
Requires-Dist: pyyaml (>=5.3.1,<6.0.0)
Requires-Dist: rich (>=4,<11)
Requires-Dist: typing_inspect (>=0.6.0,<0.7.0); python_version >= "3.7" and python_version < "3.8"
Requires-Dist: yaspin (>=0.17,<1.6)
Project-URL: Documentation, https://github.com/Ciphey/Ciphey/wiki
